LICENSE.ZPL
changes.txt
setup.py
docs/todo.txt
src/ore/__init__.py
src/ore.alchemist.egg-info/PKG-INFO
src/ore.alchemist.egg-info/SOURCES.txt
src/ore.alchemist.egg-info/dependency_links.txt
src/ore.alchemist.egg-info/namespace_packages.txt
src/ore.alchemist.egg-info/not-zip-safe
src/ore.alchemist.egg-info/requires.txt
src/ore.alchemist.egg-info/top_level.txt
src/ore/alchemist/__init__.py
src/ore/alchemist/configure.zcml
src/ore/alchemist/container.py
src/ore/alchemist/container.txt
src/ore/alchemist/graphviz.py
src/ore/alchemist/interfaces.py
src/ore/alchemist/introspector.py
src/ore/alchemist/keyreference.py
src/ore/alchemist/keyreference.txt
src/ore/alchemist/manager.py
src/ore/alchemist/meta.zcml
src/ore/alchemist/model.py
src/ore/alchemist/property.py
src/ore/alchemist/readme.txt
src/ore/alchemist/sa2zs.py
src/ore/alchemist/session.py
src/ore/alchemist/vocabulary.py
src/ore/alchemist/vocabulary.txt
src/ore/alchemist/zcml.py
src/ore/alchemist/zs2sa.py
src/ore/alchemist/tests/__init__.py
src/ore/alchemist/tests/test_container.py
src/ore/alchemist/tests/test_sa2zs.py
src/ore/alchemist/tests/test_zs2sa.py
src/ore/alchemist/tests/txncheck.py