Metadata-Version: 1.0
Name: ore.alchemist
Version: 0.6.0
Summary: sqlalchemy zope3 integration
Home-page: http://code.google.com/p/zope-alchemist
Author: Kapil Thangavelu
Author-email: kapil.foss@gmail.com
License: ZPL
Keywords: zope zope3
Platform: UNKNOWN
